MANIFEST.in
README.rst
setup.py
XStatic_ExtJS.egg-info/PKG-INFO
XStatic_ExtJS.egg-info/SOURCES.txt
XStatic_ExtJS.egg-info/dependency_links.txt
XStatic_ExtJS.egg-info/namespace_packages.txt
XStatic_ExtJS.egg-info/not-zip-safe
XStatic_ExtJS.egg-info/top_level.txt
xstatic/__init__.py
xstatic/pkg/__init__.py
xstatic/pkg/extjs/__init__.py
xstatic/pkg/extjs/data/INCLUDE_ORDER.txt
xstatic/pkg/extjs/data/ext-all-debug-w-comments.js
xstatic/pkg/extjs/data/ext-all-debug.js
xstatic/pkg/extjs/data/ext-all.js
xstatic/pkg/extjs/data/gpl-3.0.txt
xstatic/pkg/extjs/data/license.txt
xstatic/pkg/extjs/data/adapter/ext/ext-base-debug.js
xstatic/pkg/extjs/data/adapter/ext/ext-base.js
xstatic/pkg/extjs/data/adapter/jquery/ext-jquery-adapter-debug.js
xstatic/pkg/extjs/data/adapter/jquery/ext-jquery-adapter.js
xstatic/pkg/extjs/data/adapter/prototype/ext-prototype-adapter-debug.js
xstatic/pkg/extjs/data/adapter/prototype/ext-prototype-adapter.js
xstatic/pkg/extjs/data/adapter/yui/ext-yui-adapter-debug.js
xstatic/pkg/extjs/data/adapter/yui/ext-yui-adapter.js
xstatic/pkg/extjs/data/resources/charts.swf
xstatic/pkg/extjs/data/resources/expressinstall.swf
xstatic/pkg/extjs/data/resources/css/debug.css
xstatic/pkg/extjs/data/resources/css/ext-all-notheme.css
xstatic/pkg/extjs/data/resources/css/ext-all.css
xstatic/pkg/extjs/data/resources/css/reset-min.css
xstatic/pkg/extjs/data/resources/css/xtheme-access.css
xstatic/pkg/extjs/data/resources/css/xtheme-blue.css
xstatic/pkg/extjs/data/resources/css/xtheme-gray.css
xstatic/pkg/extjs/data/resources/css/yourtheme.css
xstatic/pkg/extjs/data/resources/css/structure/borders.css
xstatic/pkg/extjs/data/resources/css/structure/box.css
xstatic/pkg/extjs/data/resources/css/structure/button.css
xstatic/pkg/extjs/data/resources/css/structure/combo.css
xstatic/pkg/extjs/data/resources/css/structure/core.css
xstatic/pkg/extjs/data/resources/css/structure/date-picker.css
xstatic/pkg/extjs/data/resources/css/structure/dd.css
xstatic/pkg/extjs/data/resources/css/structure/debug.css
xstatic/pkg/extjs/data/resources/css/structure/dialog.css
xstatic/pkg/extjs/data/resources/css/structure/editor.css
xstatic/pkg/extjs/data/resources/css/structure/form.css
