Metadata-Version: 1.0
Name: XStatic-ExtJS
Version: 3.4.1.1.1
Summary: ExtJS 3.4.1.1 (XStatic packaging standard)
Home-page: http://www.sencha.com/products/extjs/
Author: Krzysztof Warunek
Author-email: krzysztof@warunek.net
License: (same as ExtJS)
Keywords: extjs xstatic
Platform: any
